{
  "meta" : {
    "appVersion" : "1.0",
    "buildNumber" : "1",
    "isoTimestamp" : "2026-02-08T105114Z"
  },
  "rawRef" : {
    "filename" : "SODS-AuditRaw-2026-02-08T105113Z.json"
  },
  "summary" : {
    "aliveHosts" : 15,
    "bleDevices" : 27,
    "errors" : 21,
    "evidenceCount" : 255,
    "highConfidenceHosts" : 0,
    "interestingHosts" : 3,
    "piAuxEvents" : 0,
    "topBLE" : [
      " (127 dBm)",
      " (127 dBm)",
      " (127 dBm)",
      " (-25 dBm)",
      " (-27 dBm)"
    ],
    "topHosts" : [
      "192.168.8.1 Low (5)",
      "192.168.8.107 Low (5)",
      "192.168.8.114 Low (5)",
      "192.168.8.152 Low (5)",
      "192.168.8.160 Low (5)"
    ],
    "totalHosts" : 254,
    "warnings" : 0
  }
}